[
    {
        "직업명": "항공기객실사무장",
        "직업설명": "기내 서비스를 제공하는 객실승무원들의 활동을 조정·감독한다.",
        "수행직무/하는일": "탑승예정인 항공기의 종류 및 목적지를 확인하고 승무원의 명단, 귀빈 명단을 확인한다. 객실승무원들에게 항로, 목적지, 귀빈에 대한 정보를 제공하고 기내에서의 근무 구역을 배치한다. 객실승무원의 업무를 총괄하고 복장 및 근무상황을 감독한다. 객실을 점검하고 탑승인원을 점검하여 기장에게 보고한다. 승객의 질문에 응대하고 요구사항을 처리한다.",
        "detail": {
            "정규교육": "12년 초과 ~ 14년 이하(전문대졸 정도)",
            "숙련기간": "4년 초과 ~ 10년 이하",
            "직무기능": "자료 (조정) / 사람 (감독) / 사물 (관련없음)",
            "작업강도": "보통 작업",
            "육체활동": "균형감각",
            "작업장소": "실내",
            "작업환경": "위험내재",
            "유사명칭": "",
            "관련직업": "",
            "자격/면허": "",
            "고용직업분류": "[5221]항공기 객실승무원",
            "표준직업분류": "[4311]항공기 객실 승무원",
            "표준산업분류": "[H511]항공 여객 운송업 / [H512]항공 화물 운송업",
            "조사연도": "2012",
            "비고": ""
        },
        "고용직업분류직업분류_1": "52. 여행·숙박·오락 서비스직",
        "고용직업분류직업분류_2": "522. 항공기·선박·열차 객실승무원",
        "고용직업분류직업분류_3": "5221. 항공기 객실승무원",
        "고용직업분류직업분류_3_설명": "항공기 여객의 편의와 안전을 도모하기 위해 각종 서비스를 제공하는 자를 말한다. 객실승무원의 활동을 감독하는 객실 사무장도 여기에 포함된다."
    },
    {
        "직업명": "항공기객실승무원",
        "직업설명": "항공기에 탑승한 승객에게 기내에서 제반 서비스를 제공한다.",
        "수행직무/하는일": "항공기객실사무장의 지시에 따라 기내를 정돈하고 목적지, 비행시간, 항로 및 귀빈 탑승현황 등에 대하여 확인한다. 항공기에 탑승한 승객이 제시하는 좌석표를 확인하여 좌석을 안내하고 인원을 점검한다. 승객의 안전 및 비상상황을 대비한 행동요령을 안내하고 승객에게 신문, 식사, 면세품 등을 제공한다. 승객의 수하물 운반을 돕고 문의에 응대한다. 비상시 비상탈출설비를 가동하여 승객의 탈출을 돕는다. 운항과 관련된 각종 일지를 작성한다.",
        "detail": {
            "정규교육": "12년 초과 ~ 14년 이하(전문대졸 정도)",
            "숙련기간": "2년 초과 ~ 4년 이하",
            "직무기능": "자료 (비교) / 사람 (서비스 제공) / 사물 (관련없음)",
            "작업강도": "보통 작업",
            "육체활동": "균형감각",
            "작업장소": "실내",
            "작업환경": "위험내재",
            "유사명칭": "",
            "관련직업": "스튜어디스, 스튜어드",
            "자격/면허": "",
            "고용직업분류": "[5221]항공기 객실승무원",
            "표준직업분류": "[4311]항공기 객실 승무원",
            "표준산업분류": "[H511]항공 여객 운송업 / [H512]항공 화물 운송업",
            "조사연도": "2012",
            "비고": ""
        },
        "고용직업분류직업분류_1": "52. 여행·숙박·오락 서비스직",
        "고용직업분류직업분류_2": "522. 항공기·선박·열차 객실승무원",
        "고용직업분류직업분류_3": "5221. 항공기 객실승무원",
        "고용직업분류직업분류_3_설명": "항공기 여객의 편의와 안전을 도모하기 위해 각종 서비스를 제공하는 자를 말한다. 객실승무원의 활동을 감독하는 객실 사무장도 여기에 포함된다."
    }
]